<?xml version="1.0" encoding="UTF-8"?>
<persistence xmlns="http://java.sun.com/xml/ns/persistence" version="2.0">

    <persistence-unit name="NewPersistenceUnit">
        <provider>org.hibernate.jpa.HibernatePersistenceProvider</provider>
        <class>cn.gson.prohis.model.pojos.TyhCashEntity</class>
        <class>cn.gson.prohis.model.pojos.TyhHosnotEntity</class>
        <class>cn.gson.prohis.model.pojos.TyhHosregEntity</class>
        <class>cn.gson.prohis.model.pojos.TyhPatientEntity</class>
        <class>cn.gson.prohis.model.pojos.TyhInpatientEntity</class>
        <class>cn.gson.prohis.model.pojos.TyhHospitalEntity</class>
        <properties>
            <property name="hibernate.connection.url" value="jdbc:mysql://rm-wz9e0163453eu84559o.mysql.rds.aliyuncs.com:3306/myhis"/>
            <property name="hibernate.connection.driver_class" value="com.mysql.cj.jdbc.Driver"/>
            <property name="hibernate.connection.username" value="root"/>
            <property name="hibernate.connection.password" value="123456"/>
            <property name="hibernate.archive.autodetection" value="class"/>
            <property name="hibernate.show_sql" value="true"/>
            <!--<property name="hibernate.format_sql" value="true"/>-->
            <!--<property name="hibernate.hbm2ddl.auto" value="update"/>-->
        </properties>
    </persistence-unit>
</persistence>
